pal_tsne-0.1.0.dist-info/METADATA
pal_tsne-0.1.0.dist-info/RECORD
pal_tsne-0.1.0.dist-info/WHEEL
pal_tsne-0.1.0.dist-info/entry_points.txt
pal_tsne-0.1.0.dist-info/top_level.txt
tsne/__init__.py
tsne/cli.py
tsne/common.py
tsne/main.py
tsne/tsne.py
