Metadata-Version: 2.1
Name: pal-tsne
Version: 0.1.0
Summary: parallel tsne
Home-page: https://github.com/MingChaoXu/paralell-tsne
Author: xenos
Author-email: mingchao.xu.casia@gmail.com
License: MIT Licence
Keywords: pip,tsne,parallel,xenos
Platform: any
Requires-Python: >=3.6.0
Requires-Dist: requests
Requires-Dist: click
